pydictionaria/__init__.py
pydictionaria/concepts.py
pydictionaria/example.py
pydictionaria/flextext.py
pydictionaria/log.py
pydictionaria/preprocess_lib.py
pydictionaria/scaffold.py
pydictionaria/sfm2cldf.py
pydictionaria/sfm_lib.py
pydictionaria/util.py
pydictionaria/commands/__init__.py
pydictionaria/commands/release.py
pydictionaria/commands/upload_media.py
pydictionaria/dataset_template/+prefix+_+id+.py_tmpl
pydictionaria/dataset_template/.gitignore
pydictionaria/dataset_template/pyproject.toml_tmpl
pydictionaria/dataset_template/setup.py
pydictionaria/dataset_template/test.py
pydictionaria/dataset_template/.github/workflows/python-package.yml
pydictionaria/dataset_template/cldf/.gitattributes
pydictionaria/dataset_template/cldf/README.md
pydictionaria/dataset_template/etc/README.md
pydictionaria/dataset_template/etc/md.json
pydictionaria/dataset_template/raw/README.md
pydictionaria-2.3.dist-info/LICENSE
pydictionaria-2.3.dist-info/METADATA
pydictionaria-2.3.dist-info/WHEEL
pydictionaria-2.3.dist-info/entry_points.txt
pydictionaria-2.3.dist-info/top_level.txt
pydictionaria-2.3.dist-info/RECORD
